geotify/__init__.py
geotify/command.py
geotify/map.py
geotify/utils.py
geotify/datasets/Map_Korea.json
geotify/datasets/TL_SCCO_CTPRVN.json
geotify/datasets/aaa.csv
geotify/datasets/base_korea_map.json
geotify/datasets/강원도.csv
geotify/datasets/서울_인구밀도.csv
geotify/datasets/전북특별자치도_인구밀도.csv
geotify-0.2.0.dist-info/METADATA
geotify-0.2.0.dist-info/WHEEL
geotify-0.2.0.dist-info/entry_points.txt
geotify-0.2.0.dist-info/top_level.txt
geotify-0.2.0.dist-info/RECORD
